copilot_ollama_windows/__init__.py
copilot_ollama_windows/run.ps1
copilot_ollama_windows/start.py
copilot_ollama_windows-1.0.2.dist-info/WHEEL
copilot_ollama_windows-1.0.2.dist-info/entry_points.txt
copilot_ollama_windows-1.0.2.dist-info/METADATA
copilot_ollama_windows-1.0.2.dist-info/RECORD
