Metadata-Version: 2.3
Name: copilot-ollama-windows
Version: 1.0.2
Summary: Windows support for copilot-ollama
Author: Jordan Miller, Bas Steins
Requires-Dist: fastapi>=0.115.14,<0.117.0
Requires-Dist: httpx[http2]~=0.28.1
Requires-Dist: litellm[proxy]>=1.77.1
Requires-Dist: oai2ollama>=1.2.6
Requires-Dist: pydantic-settings~=2.10.1
Requires-Dist: uvicorn-hmr~=0.0.8.0
Requires-Python: >=3.12
Project-URL: repository, https://github.com/jm6271/copilot-ollama-windows
